README.md
setup.cfg
setup.py
lol_beautify_gdocs/__init__.py
lol_beautify_gdocs/beautify_document.py
lol_beautify_gdocs/gdocs_utils.py
lol_beautify_gdocs/hardcoded_variables.py
lol_beautify_gdocs.egg-info/PKG-INFO
lol_beautify_gdocs.egg-info/SOURCES.txt
lol_beautify_gdocs.egg-info/dependency_links.txt
lol_beautify_gdocs.egg-info/requires.txt
lol_beautify_gdocs.egg-info/top_level.txt