Metadata-Version: 1.1
Name: lol-beautify-gdocs
Version: 0.1
Summary: Beautifying Google documents related to League of Legends
Home-page: https://github.com/mrtolkien
Author: Gary Mialaret
Author-email: gary.mialaret@gmail.com
License: MIT
Download-URL: https://github.com/mrtolkien/lol_beautify_gdocs/archive/v0.1-alpha.tar.gz
Keywords: lol,gdocs
Platform: UNKNOWN
Classifier: Development Status :: 3 - Alpha
Classifier: Intended Audience :: Developers
Classifier: License :: OSI Approved :: MIT License
Classifier: Programming Language :: Python :: 3.8
